{"https://gallica.bnf.fr/iiif/ark:/12148/btv1b8419219x/f12/173,453,2997,4314/full/0/native.jpg-1":{"filename":"https://gallica.bnf.fr/iiif/ark:/12148/btv1b8419219x/f12/173,453,2997,4314/full/0/native.jpg","size":-1,"regions":[{"shape_attributes":{"name":"rect","x":1937,"y":1705,"width":287,"height":1854},"region_attributes":{"Descripteur":"canne","Type":"objet"}},{"shape_attributes":{"name":"rect","x":1292,"y":1109,"width":392,"height":2666},"region_attributes":{"Descripteur":"colonne","Type":"objet"}},{"shape_attributes":{"name":"rect","x":392,"y":1518,"width":397,"height":673},"region_attributes":{"Descripteur":"croix","Type":"objet"}},{"shape_attributes":{"name":"rect","x":1777,"y":767,"width":861,"height":690},"region_attributes":{"Descripteur":"nimbe","Type":"objet"}},{"shape_attributes":{"name":"rect","x":149,"y":1446,"width":1176,"height":2279},"region_attributes":{"Descripteur":"vêtement","Type":"objet"}}],"file_attributes":{"MandragoreId":"1009"}},"https://gallica.bnf.fr/iiif/ark:/12148/btv1b8419219x/f22/181,550,2513,1709/full/0/native.jpg-1":{"filename":"https://gallica.bnf.fr/iiif/ark:/12148/btv1b8419219x/f22/181,550,2513,1709/full/0/native.jpg","size":-1,"regions":[{"shape_attributes":{"name":"rect","x":1010,"y":793,"width":566,"height":367},"region_attributes":{"Descripteur":"bouquet","Type":"objet"}},{"shape_attributes":{"name":"rect","x":378,"y":177,"width":328,"height":219},"region_attributes":{"Descripteur":"couronne","Type":"objet"}},{"shape_attributes":{"name":"rect","x":312,"y":671,"width":433,"height":146},"region_attributes":{"Descripteur":"fourrure","Type":"objet"}},{"shape_attributes":{"name":"rect","x":1099,"y":323,"width":179,"height":225},"region_attributes":{"Descripteur":"lampe","Type":"objet"}},{"shape_attributes":{"name":"rect","x":1276,"y":153,"width":450,"height":409},"region_attributes":{"Descripteur":"nimbe","Type":"objet"}},{"shape_attributes":{"name":"rect","x":1945,"y":212,"width":487,"height":728},"region_attributes":{"Descripteur":"rideau","Type":"objet"}},{"shape_attributes":{"name":"rect","x":291,"y":186,"width":750,"height":1429},"region_attributes":{"Descripteur":"roi","Type":"personne"}},{"shape_attributes":{"name":"rect","x":87,"y":433,"width":929,"height":1149},"region_attributes":{"Descripteur":"trône","Type":"objet"}},{"shape_attributes":{"name":"rect","x":1062,"y":1130,"width":409,"height":518},"region_attributes":{"Descripteur":"vase","Type":"objet"}},{"shape_attributes":{"name":"rect","x":295,"y":660,"width":612,"height":948},"region_attributes":{"Descripteur":"vêtement","Type":"objet"}},{"shape_attributes":{"name":"rect","x":1153,"y":104,"width":1186,"height":1590},"region_attributes":{"Descripteur":"moine","Type":"objet"}}],"file_attributes":{"MandragoreId":"1010"}},"https://gallica.bnf.fr/iiif/ark:/12148/btv1b8419219x/f31/821,681,2355,2081/full/0/native.jpg-1":{"filename":"https://gallica.bnf.fr/iiif/ark:/12148/btv1b8419219x/f31/821,681,2355,2081/full/0/native.jpg","size":-1,"regions":[{"shape_attributes":{"name":"rect","x":519,"y":130,"width":325,"height":237},"region_attributes":{"Descripteur":"couronne","Type":"objet"}},{"shape_attributes":{"name":"rect","x":1474,"y":210,"width":184,"height":271},"region_attributes":{"Descripteur":"lampe","Type":"objet"}},{"shape_attributes":{"name":"rect","x":80,"y":0,"width":633,"height":769},"region_attributes":{"Descripteur":"rideau","Type":"objet"}},{"shape_attributes":{"name":"rect","x":399,"y":120,"width":790,"height":1472},"region_attributes":{"Descripteur":"roi","Type":"personne"}},{"shape_attributes":{"name":"rect","x":226,"y":564,"width":383,"height":931},"region_attributes":{"Descripteur":"trône","Type":"objet"}},{"shape_attributes":{"name":"rect","x":1307,"y":708,"width":349,"height":192},"region_attributes":{"Descripteur":"turban","Type":"objet"}},{"shape_attributes":{"name":"rect","x":1785,"y":531,"width":526,"height":1469},"region_attributes":{"Descripteur":"astrologue","Type":"objet"}},{"shape_attributes":{"name":"rect","x":1064,"y":678,"width":699,"height":1314},"region_attributes":{"Descripteur":"scribe","Type":"objet"}},{"shape_attributes":{"name":"rect","x":1038,"y":1291,"width":463,"height":239},"region_attributes":{"Descripteur":"tablette","Type":"objet"}},{"shape_attributes":{"name":"rect","x":376,"y":528,"width":741,"height":1028},"region_attributes":{"Descripteur":"vêtement","Type":"objet"}}],"file_attributes":{"MandragoreId":"1011"}},"https://gallica.bnf.fr/iiif/ark:/12148/btv1b8419219x/f32/254,1636,2371,2745/full/0/native.jpg-1":{"filename":"https://gallica.bnf.fr/iiif/ark:/12148/btv1b8419219x/f32/254,1636,2371,2745/full/0/native.jpg","size":-1,"regions":[{"shape_attributes":{"name":"rect","x":1542,"y":2065,"width":126,"height":615},"region_attributes":{"Descripteur":"canne","Type":"objet"}},{"shape_attributes":{"name":"rect","x":109,"y":1879,"width":246,"height":372},"region_attributes":{"Descripteur":"chope","Type":"objet"}},{"shape_attributes":{"name":"rect","x":158,"y":306,"width":316,"height":151},"region_attributes":{"Descripteur":"couronne","Type":"objet"}},{"shape_attributes":{"name":"rect","x":1549,"y":1300,"width":769,"height":836},"region_attributes":{"Descripteur":"escalier","Type":"objet"}},{"shape_attributes":{"name":"rect","x":105,"y":2287,"width":186,"height":292},"region_attributes":{"Descripteur":"feu","Type":"objet"}},{"shape_attributes":{"name":"rect","x":133,"y":622,"width":316,"height":126},"region_attributes":{"Descripteur":"fourrure","Type":"objet"}},{"shape_attributes":{"name":"rect","x":759,"y":365,"width":299,"height":235},"region_attributes":{"Descripteur":"turban","Type":"objet"}},{"shape_attributes":{"name":"rect","x":2010,"y":808,"width":335,"height":245},"region_attributes":{"Descripteur":"coiffe","Type":"objet"}},{"shape_attributes":{"name":"rect","x":571,"y":1813,"width":198,"height":198},"region_attributes":{"Descripteur":"coupe","Type":"objet"}},{"shape_attributes":{"name":"rect","x":52,"y":1478,"width":1344,"height":1241},"region_attributes":{"Descripteur":"cuisine","Type":"objet"}},{"shape_attributes":{"name":"rect","x":17,"y":39,"width":2337,"height":2676},"region_attributes":{"Descripteur":"palais","Type":"notion"}},{"shape_attributes":{"name":"rect","x":1490,"y":769,"width":606,"height":344},"region_attributes":{"Descripteur":"plateau","Type":"objet"}},{"shape_attributes":{"name":"rect","x":606,"y":331,"width":507,"height":1044},"region_attributes":{"Descripteur":"savant","Type":"objet"}},{"shape_attributes":{"name":"rect","x":1396,"y":588,"width":932,"height":1301},"region_attributes":{"Descripteur":"serviteur","Type":"objet"}}],"file_attributes":{"MandragoreId":"1012"}},"https://gallica.bnf.fr/iiif/ark:/12148/btv1b8419219x/f39/797,2679,2436,1975/full/0/native.jpg-1":{"filename":"https://gallica.bnf.fr/iiif/ark:/12148/btv1b8419219x/f39/797,2679,2436,1975/full/0/native.jpg","size":-1,"regions":[{"shape_attributes":{"name":"rect","x":1505,"y":755,"width":174,"height":1043},"region_attributes":{"Descripteur":"canne","Type":"objet"}},{"shape_attributes":{"name":"rect","x":91,"y":293,"width":841,"height":1366},"region_attributes":{"Descripteur":"cavalier","Type":"personne"}},{"shape_attributes":{"name":"rect","x":2161,"y":1010,"width":184,"height":417},"region_attributes":{"Descripteur":"chapelet","Type":"objet"}},{"shape_attributes":{"name":"rect","x":40,"y":523,"width":1381,"height":1421},"region_attributes":{"Descripteur":"cheval","Type":"objet"}},{"shape_attributes":{"name":"rect","x":548,"y":247,"width":346,"height":197},"region_attributes":{"Descripteur":"couronne","Type":"objet"}},{"shape_attributes":{"name":"rect","x":2232,"y":1300,"width":101,"height":129},"region_attributes":{"Descripteur":"croix","Type":"objet"}},{"shape_attributes":{"name":"rect","x":61,"y":247,"width":1219,"height":1441},"region_attributes":{"Descripteur":"lance","Type":"objet"}},{"shape_attributes":{"name":"rect","x":1237,"y":331,"width":778,"height":1328},"region_attributes":{"Descripteur":"moine","Type":"personne"}},{"shape_attributes":{"name":"rect","x":164,"y":268,"width":747,"height":1381},"region_attributes":{"Descripteur":"roi","Type":"personne"}},{"shape_attributes":{"name":"rect","x":1848,"y":747,"width":530,"height":982},"region_attributes":{"Descripteur":"vêtement","Type":"objet"}},{"shape_attributes":{"name":"rect","x":239,"y":823,"width":671,"height":761},"region_attributes":{"Descripteur":"tapis.de.selle","Type":"objet"}},{"shape_attributes":{"name":"rect","x":819,"y":551,"width":508,"height":446},"region_attributes":{"Descripteur":"harnais","Type":"objet"}},{"shape_attributes":{"name":"rect","x":1207,"y":185,"width":1200,"height":1671},"region_attributes":{"Descripteur":"bénédiction","Type":"scène"}}],"file_attributes":{"MandragoreId":"1013"}},"https://gallica.bnf.fr/iiif/ark:/12148/btv1b8419219x/f43/839,2244,2441,1640/full/0/native.jpg-1":{"filename":"https://gallica.bnf.fr/iiif/ark:/12148/btv1b8419219x/f43/839,2244,2441,1640/full/0/native.jpg","size":-1,"regions":[{"shape_attributes":{"name":"rect","x":552,"y":747,"width":518,"height":185},"region_attributes":{"Descripteur":"fourrure","Type":"objet"}},{"shape_attributes":{"name":"rect","x":193,"y":222,"width":463,"height":1086},"region_attributes":{"Descripteur":"rideau","Type":"objet"}},{"shape_attributes":{"name":"rect","x":1642,"y":327,"width":384,"height":294},"region_attributes":{"Descripteur":"turban","Type":"objet"}},{"shape_attributes":{"name":"rect","x":11,"y":138,"width":2408,"height":1478},"region_attributes":{"Descripteur":"palais","Type":"notion"}},{"shape_attributes":{"name":"rect","x":1475,"y":254,"width":657,"height":1351},"region_attributes":{"Descripteur":"précepteur","Type":"objet"}},{"shape_attributes":{"name":"rect","x":327,"y":687,"width":973,"height":915},"region_attributes":{"Descripteur":"vêtement","Type":"objet"}},{"shape_attributes":{"name":"rect","x":1784,"y":821,"width":138,"height":94},"region_attributes":{"Descripteur":"fermail","Type":"objet"}}],"file_attributes":{"MandragoreId":"1014"}},"https://gallica.bnf.fr/iiif/ark:/12148/btv1b8419219x/f47/832,584,2399,1961/full/0/native.jpg-1":{"filename":"https://gallica.bnf.fr/iiif/ark:/12148/btv1b8419219x/f47/832,584,2399,1961/full/0/native.jpg","size":-1,"regions":[{"shape_attributes":{"name":"rect","x":211,"y":148,"width":832,"height":1424},"region_attributes":{"Descripteur":"cavalier","Type":"personne"}},{"shape_attributes":{"name":"rect","x":83,"y":504,"width":1193,"height":1273},"region_attributes":{"Descripteur":"cheval","Type":"objet"}},{"shape_attributes":{"name":"rect","x":697,"y":183,"width":361,"height":218},"region_attributes":{"Descripteur":"couronne","Type":"objet"}},{"shape_attributes":{"name":"rect","x":1466,"y":521,"width":173,"height":727},"region_attributes":{"Descripteur":"flûte","Type":"objet"}},{"shape_attributes":{"name":"rect","x":817,"y":584,"width":451,"height":366},"region_attributes":{"Descripteur":"harnais","Type":"objet"}},{"shape_attributes":{"name":"rect","x":95,"y":198,"width":1283,"height":1654},"region_attributes":{"Descripteur":"lance","Type":"objet"}},{"shape_attributes":{"name":"rect","x":1251,"y":246,"width":484,"height":1564},"region_attributes":{"Descripteur":"musicien","Type":"personne"}},{"shape_attributes":{"name":"rect","x":1685,"y":593,"width":557,"height":461},"region_attributes":{"Descripteur":"tambourin","Type":"objet"}},{"shape_attributes":{"name":"rect","x":1324,"y":271,"width":306,"height":216},"region_attributes":{"Descripteur":"turban","Type":"objet"}},{"shape_attributes":{"name":"rect","x":307,"y":750,"width":664,"height":628},"region_attributes":{"Descripteur":"tapis.de.selle","Type":"objet"}}],"file_attributes":{"MandragoreId":"1015"}},"https://gallica.bnf.fr/iiif/ark:/12148/btv1b8419219x/f52/136,777,2356,1767/full/0/native.jpg-1":{"filename":"https://gallica.bnf.fr/iiif/ark:/12148/btv1b8419219x/f52/136,777,2356,1767/full/0/native.jpg","size":-1,"regions":[{"shape_attributes":{"name":"rect","x":1071,"y":553,"width":59,"height":68},"region_attributes":{"Descripteur":"croix","Type":"objet"}},{"shape_attributes":{"name":"rect","x":1746,"y":181,"width":361,"height":285},"region_attributes":{"Descripteur":"turban","Type":"objet"}},{"shape_attributes":{"name":"rect","x":1340,"y":917,"width":325,"height":348},"region_attributes":{"Descripteur":"chapelet","Type":"objet"}},{"shape_attributes":{"name":"rect","x":678,"y":402,"width":237,"height":768},"region_attributes":{"Descripteur":"colonne","Type":"objet"}},{"shape_attributes":{"name":"rect","x":206,"y":727,"width":400,"height":122},"region_attributes":{"Descripteur":"fourrure","Type":"objet"}}],"file_attributes":{"MandragoreId":"1016"}},"https://gallica.bnf.fr/iiif/ark:/12148/btv1b8419219x/f54/120,2605,2320,1813/full/0/native.jpg-1":{"filename":"https://gallica.bnf.fr/iiif/ark:/12148/btv1b8419219x/f54/120,2605,2320,1813/full/0/native.jpg","size":-1,"regions":[{"shape_attributes":{"name":"rect","x":1398,"y":955,"width":322,"height":311},"region_attributes":{"Descripteur":"chapelet","Type":"objet"}},{"shape_attributes":{"name":"rect","x":647,"y":359,"width":385,"height":160},"region_attributes":{"Descripteur":"couronne","Type":"objet"}},{"shape_attributes":{"name":"rect","x":1402,"y":1161,"width":109,"height":123},"region_attributes":{"Descripteur":"croix","Type":"objet"}},{"shape_attributes":{"name":"rect","x":538,"y":684,"width":433,"height":148},"region_attributes":{"Descripteur":"fourrure","Type":"objet"}},{"shape_attributes":{"name":"rect","x":1277,"y":313,"width":167,"height":285},"region_attributes":{"Descripteur":"lampe","Type":"objet"}},{"shape_attributes":{"name":"rect","x":100,"y":95,"width":2132,"height":1212},"region_attributes":{"Descripteur":"palais","Type":"notion"}},{"shape_attributes":{"name":"rect","x":331,"y":1106,"width":1048,"height":628},"region_attributes":{"Descripteur":"trône","Type":"objet"}},{"shape_attributes":{"name":"rect","x":148,"y":1048,"width":188,"height":350},"region_attributes":{"Descripteur":"vase","Type":"objet"}},{"shape_attributes":{"name":"rect","x":473,"y":694,"width":763,"height":666},"region_attributes":{"Descripteur":"vêtement","Type":"objet"}},{"shape_attributes":{"name":"rect","x":90,"y":1281,"width":325,"height":180},"region_attributes":{"Descripteur":"plateau","Type":"objet"}}],"file_attributes":{"MandragoreId":"1017"}},"https://gallica.bnf.fr/iiif/ark:/12148/btv1b8419219x/f58/151,939,2565,1821/full/0/native.jpg-1":{"filename":"https://gallica.bnf.fr/iiif/ark:/12148/btv1b8419219x/f58/151,939,2565,1821/full/0/native.jpg","size":-1,"regions":[{"shape_attributes":{"name":"rect","x":1419,"y":242,"width":536,"height":1479},"region_attributes":{"Descripteur":"ascète","Type":"personne"}},{"shape_attributes":{"name":"rect","x":256,"y":7,"width":792,"height":1428},"region_attributes":{"Descripteur":"cavalier","Type":"personne"}},{"shape_attributes":{"name":"rect","x":114,"y":331,"width":1368,"height":1416},"region_attributes":{"Descripteur":"cheval","Type":"objet"}},{"shape_attributes":{"name":"rect","x":862,"y":366,"width":459,"height":662},"region_attributes":{"Descripteur":"harnais","Type":"objet"}},{"shape_attributes":{"name":"rect","x":224,"y":23,"width":1093,"height":1554},"region_attributes":{"Descripteur":"lance","Type":"objet"}},{"shape_attributes":{"name":"rect","x":301,"y":28,"width":729,"height":1412},"region_attributes":{"Descripteur":"roi","Type":"personne"}},{"shape_attributes":{"name":"rect","x":1962,"y":492,"width":557,"height":901},"region_attributes":{"Descripteur":"peau.de.bête","Type":"notion"}}],"file_attributes":{"MandragoreId":"1018"}},"https://gallica.bnf.fr/iiif/ark:/12148/btv1b8419219x/f60/158,1895,2649,1781/full/0/native.jpg-1":{"filename":"https://gallica.bnf.fr/iiif/ark:/12148/btv1b8419219x/f60/158,1895,2649,1781/full/0/native.jpg","size":-1,"regions":[{"shape_attributes":{"name":"rect","x":1121,"y":1162,"width":399,"height":235},"region_attributes":{"Descripteur":"coffret","Type":"objet"}},{"shape_attributes":{"name":"rect","x":1034,"y":225,"width":219,"height":317},"region_attributes":{"Descripteur":"lampe","Type":"objet"}},{"shape_attributes":{"name":"rect","x":260,"y":89,"width":893,"height":1376},"region_attributes":{"Descripteur":"roi","Type":"personne"}},{"shape_attributes":{"name":"rect","x":64,"y":708,"width":1057,"height":982},"region_attributes":{"Descripteur":"trône","Type":"objet"}},{"shape_attributes":{"name":"rect","x":1768,"y":182,"width":328,"height":255},"region_attributes":{"Descripteur":"turban","Type":"objet"}}],"file_attributes":{"MandragoreId":"1019"}},"https://gallica.bnf.fr/iiif/ark:/12148/btv1b8419219x/f95/570,697,2634,1653/full/0/native.jpg-1":{"filename":"https://gallica.bnf.fr/iiif/ark:/12148/btv1b8419219x/f95/570,697,2634,1653/full/0/native.jpg","size":-1,"regions":[{"shape_attributes":{"name":"rect","x":364,"y":93,"width":1559,"height":1437},"region_attributes":{"Descripteur":"arbre","Type":"objet"}},{"shape_attributes":{"name":"rect","x":120,"y":451,"width":2374,"height":1102},"region_attributes":{"Descripteur":"chasse","Type":"scène"}},{"shape_attributes":{"name":"rect","x":1304,"y":837,"width":1166,"height":711},"region_attributes":{"Descripteur":"filet","Type":"objet"}},{"shape_attributes":{"name":"rect","x":1877,"y":98,"width":566,"height":766},"region_attributes":{"Descripteur":"palmier","Type":"objet"}},{"shape_attributes":{"name":"rect","x":631,"y":788,"width":1834,"height":768},"region_attributes":{"Descripteur":"piège","Type":"objet"}},{"shape_attributes":{"name":"rect","x":1335,"y":89,"width":406,"height":171},"region_attributes":{"Descripteur":"rossignol","Type":"objet"}},{"shape_attributes":{"name":"rect","x":455,"y":446,"width":378,"height":262},"region_attributes":{"Descripteur":"turban","Type":"objet"}},{"shape_attributes":{"name":"rect","x":59,"y":1168,"width":639,"height":376},"region_attributes":{"Descripteur":"étoffe","Type":"notion"}}],"file_attributes":{"MandragoreId":"1020"}},"https://gallica.bnf.fr/iiif/ark:/12148/btv1b8419219x/f120/83,2084,3088,2415/full/0/native.jpg-1":{"filename":"https://gallica.bnf.fr/iiif/ark:/12148/btv1b8419219x/f120/83,2084,3088,2415/full/0/native.jpg","size":-1,"regions":[{"shape_attributes":{"name":"rect","x":2081,"y":46,"width":892,"height":1881},"region_attributes":{"Descripteur":"arbre","Type":"objet"}},{"shape_attributes":{"name":"rect","x":2245,"y":1828,"width":831,"height":553},"region_attributes":{"Descripteur":"rat","Type":"objet"}},{"shape_attributes":{"name":"rect","x":726,"y":1774,"width":345,"height":570},"region_attributes":{"Descripteur":"serpent","Type":"objet"}},{"shape_attributes":{"name":"rect","x":630,"y":380,"width":1884,"height":1445},"region_attributes":{"Descripteur":"puits","Type":"objet"}},{"shape_attributes":{"name":"rect","x":1107,"y":1755,"width":1071,"height":588},"region_attributes":{"Descripteur":"dragon","Type":"objet"}},{"shape_attributes":{"name":"rect","x":14,"y":395,"width":653,"height":947},"region_attributes":{"Descripteur":"unicorne","Type":"objet"}}],"file_attributes":{"MandragoreId":"1021"}},"https://gallica.bnf.fr/iiif/ark:/12148/btv1b8419219x/f125/844,2539,2406,1898/full/0/native.jpg-1":{"filename":"https://gallica.bnf.fr/iiif/ark:/12148/btv1b8419219x/f125/844,2539,2406,1898/full/0/native.jpg","size":-1,"regions":[{"shape_attributes":{"name":"rect","x":68,"y":32,"width":1486,"height":1797},"region_attributes":{"Descripteur":"arbre","Type":"objet"}},{"shape_attributes":{"name":"rect","x":257,"y":384,"width":359,"height":187},"region_attributes":{"Descripteur":"coiffe","Type":"objet"}},{"shape_attributes":{"name":"rect","x":1588,"y":367,"width":282,"height":240},"region_attributes":{"Descripteur":"turban","Type":"objet"}},{"shape_attributes":{"name":"rect","x":57,"y":734,"width":727,"height":1124},"region_attributes":{"Descripteur":"vêtement","Type":"objet"}},{"shape_attributes":{"name":"rect","x":90,"y":1278,"width":677,"height":505},"region_attributes":{"Descripteur":"étoffe","Type":"notion"}}],"file_attributes":{"MandragoreId":"1022"}},"https://gallica.bnf.fr/iiif/ark:/12148/btv1b8419219x/f128/121,1666,2291,1959/full/0/native.jpg-1":{"filename":"https://gallica.bnf.fr/iiif/ark:/12148/btv1b8419219x/f128/121,1666,2291,1959/full/0/native.jpg","size":-1,"regions":[{"shape_attributes":{"name":"rect","x":1234,"y":844,"width":295,"height":145},"region_attributes":{"Descripteur":"ceinture","Type":"objet"}},{"shape_attributes":{"name":"rect","x":901,"y":441,"width":228,"height":1284},"region_attributes":{"Descripteur":"colonne","Type":"objet"}},{"shape_attributes":{"name":"rect","x":258,"y":273,"width":491,"height":185},"region_attributes":{"Descripteur":"couronne","Type":"objet"}},{"shape_attributes":{"name":"rect","x":165,"y":646,"width":488,"height":215},"region_attributes":{"Descripteur":"fourrure","Type":"objet"}},{"shape_attributes":{"name":"rect","x":38,"y":1708,"width":2166,"height":193},"region_attributes":{"Descripteur":"pavement","Type":"objet"}},{"shape_attributes":{"name":"rect","x":120,"y":253,"width":751,"height":1224},"region_attributes":{"Descripteur":"roi","Type":"objet"}},{"shape_attributes":{"name":"rect","x":48,"y":851,"width":826,"height":869},"region_attributes":{"Descripteur":"trône","Type":"objet"}},{"shape_attributes":{"name":"rect","x":1302,"y":203,"width":331,"height":300},"region_attributes":{"Descripteur":"turban","Type":"objet"}},{"shape_attributes":{"name":"rect","x":941,"y":678,"width":130,"height":849},"region_attributes":{"Descripteur":"décor","Type":"notion"}}],"file_attributes":{"MandragoreId":"1023"}},"https://gallica.bnf.fr/iiif/ark:/12148/btv1b8419219x/f146/107,1673,2304,1730/full/0/native.jpg-1":{"filename":"https://gallica.bnf.fr/iiif/ark:/12148/btv1b8419219x/f146/107,1673,2304,1730/full/0/native.jpg","size":-1,"regions":[{"shape_attributes":{"name":"rect","x":511,"y":987,"width":387,"height":124},"region_attributes":{"Descripteur":"ceinture","Type":"objet"}},{"shape_attributes":{"name":"rect","x":750,"y":299,"width":416,"height":232},"region_attributes":{"Descripteur":"couronne","Type":"objet"}},{"shape_attributes":{"name":"rect","x":248,"y":314,"width":992,"height":1107},"region_attributes":{"Descripteur":"roi","Type":"objet"}},{"shape_attributes":{"name":"rect","x":1301,"y":301,"width":390,"height":286},"region_attributes":{"Descripteur":"turban","Type":"objet"}},{"shape_attributes":{"name":"rect","x":31,"y":1064,"width":160,"height":518},"region_attributes":{"Descripteur":"vase","Type":"objet"}},{"shape_attributes":{"name":"rect","x":1070,"y":285,"width":998,"height":1341},"region_attributes":{"Descripteur":"vizir","Type":"objet"}},{"shape_attributes":{"name":"rect","x":141,"y":1351,"width":1138,"height":319},"region_attributes":{"Descripteur":"trône","Type":"objet"}},{"shape_attributes":{"name":"rect","x":281,"y":1142,"width":782,"height":264},"region_attributes":{"Descripteur":"étoffe","Type":"notion"}}],"file_attributes":{"MandragoreId":"1024"}},"https://gallica.bnf.fr/iiif/ark:/12148/btv1b8419219x/f147/866,2441,2378,1727/full/0/native.jpg-1":{"filename":"https://gallica.bnf.fr/iiif/ark:/12148/btv1b8419219x/f147/866,2441,2378,1727/full/0/native.jpg","size":-1,"regions":[{"shape_attributes":{"name":"rect","x":678,"y":522,"width":168,"height":146},"region_attributes":{"Descripteur":"bijou","Type":"objet"}},{"shape_attributes":{"name":"rect","x":1553,"y":842,"width":227,"height":601},"region_attributes":{"Descripteur":"bouteille","Type":"objet"}},{"shape_attributes":{"name":"rect","x":181,"y":1012,"width":750,"height":570},"region_attributes":{"Descripteur":"transparence","Type":"notion"}},{"shape_attributes":{"name":"rect","x":1178,"y":499,"width":301,"height":449},"region_attributes":{"Descripteur":"coupe","Type":"objet"}},{"shape_attributes":{"name":"rect","x":50,"y":96,"width":2240,"height":1596},"region_attributes":{"Descripteur":"grotte","Type":"scène"}},{"shape_attributes":{"name":"rect","x":67,"y":4,"width":1323,"height":1691},"region_attributes":{"Descripteur":"danseur","Type":"objet"}}],"file_attributes":{"MandragoreId":"1025"}},"https://gallica.bnf.fr/iiif/ark:/12148/btv1b8419219x/f151/762,3472,2420,1588/full/0/native.jpg-1":{"filename":"https://gallica.bnf.fr/iiif/ark:/12148/btv1b8419219x/f151/762,3472,2420,1588/full/0/native.jpg","size":-1,"regions":[{"shape_attributes":{"name":"rect","x":1518,"y":145,"width":190,"height":286},"region_attributes":{"Descripteur":"lampe","Type":"objet"}},{"shape_attributes":{"name":"rect","x":788,"y":241,"width":251,"height":1341},"region_attributes":{"Descripteur":"colonne","Type":"objet"}},{"shape_attributes":{"name":"rect","x":1100,"y":214,"width":339,"height":231},"region_attributes":{"Descripteur":"coiffe","Type":"objet"}}],"file_attributes":{"MandragoreId":"1026"}},"https://gallica.bnf.fr/iiif/ark:/12148/btv1b8419219x/f152/110,606,2342,1677/full/0/native.jpg-1":{"filename":"https://gallica.bnf.fr/iiif/ark:/12148/btv1b8419219x/f152/110,606,2342,1677/full/0/native.jpg","size":-1,"regions":[{"shape_attributes":{"name":"rect","x":315,"y":869,"width":165,"height":79},"region_attributes":{"Descripteur":"bijou","Type":"objet"}},{"shape_attributes":{"name":"rect","x":1089,"y":1101,"width":290,"height":95},"region_attributes":{"Descripteur":"ceinture","Type":"objet"}},{"shape_attributes":{"name":"rect","x":1055,"y":387,"width":335,"height":264},"region_attributes":{"Descripteur":"coiffe","Type":"objet"}},{"shape_attributes":{"name":"rect","x":760,"y":373,"width":232,"height":1152},"region_attributes":{"Descripteur":"colonne","Type":"objet"}},{"shape_attributes":{"name":"rect","x":1479,"y":161,"width":246,"height":299},"region_attributes":{"Descripteur":"lampe","Type":"objet"}},{"shape_attributes":{"name":"rect","x":70,"y":505,"width":802,"height":1133},"region_attributes":{"Descripteur":"vêtement","Type":"objet"}}],"file_attributes":{"MandragoreId":"1027"}},"https://gallica.bnf.fr/iiif/ark:/12148/btv1b8419219x/f168/51,1207,2567,1836/full/0/native.jpg-1":{"filename":"https://gallica.bnf.fr/iiif/ark:/12148/btv1b8419219x/f168/51,1207,2567,1836/full/0/native.jpg","size":-1,"regions":[{"shape_attributes":{"name":"rect","x":60,"y":108,"width":605,"height":1356},"region_attributes":{"Descripteur":"cavalier","Type":"personne"}},{"shape_attributes":{"name":"rect","x":38,"y":44,"width":2525,"height":1741},"region_attributes":{"Descripteur":"chasse","Type":"scène"}},{"shape_attributes":{"name":"rect","x":53,"y":389,"width":1080,"height":1367},"region_attributes":{"Descripteur":"cheval","Type":"objet"}},{"shape_attributes":{"name":"rect","x":270,"y":119,"width":400,"height":190},"region_attributes":{"Descripteur":"couronne","Type":"objet"}},{"shape_attributes":{"name":"rect","x":1100,"y":60,"width":771,"height":705},"region_attributes":{"Descripteur":"gazelle","Type":"objet"}},{"shape_attributes":{"name":"rect","x":543,"y":457,"width":451,"height":625},"region_attributes":{"Descripteur":"harnais","Type":"objet"}},{"shape_attributes":{"name":"rect","x":80,"y":384,"width":1016,"height":1261},"region_attributes":{"Descripteur":"lance","Type":"objet"}},{"shape_attributes":{"name":"rect","x":80,"y":119,"width":581,"height":1348},"region_attributes":{"Descripteur":"roi","Type":"personne"}},{"shape_attributes":{"name":"rect","x":103,"y":661,"width":504,"height":611},"region_attributes":{"Descripteur":"tapis.de.selle","Type":"objet"}}],"file_attributes":{"MandragoreId":"1028"}},"https://gallica.bnf.fr/iiif/ark:/12148/btv1b8419219x/f180/164,625,2310,2632/full/0/native.jpg-1":{"filename":"https://gallica.bnf.fr/iiif/ark:/12148/btv1b8419219x/f180/164,625,2310,2632/full/0/native.jpg","size":-1,"regions":[{"shape_attributes":{"name":"rect","x":973,"y":444,"width":805,"height":1306},"region_attributes":{"Descripteur":"arbre","Type":"objet"}},{"shape_attributes":{"name":"rect","x":253,"y":288,"width":1188,"height":2228},"region_attributes":{"Descripteur":"baptême","Type":"scène"}},{"shape_attributes":{"name":"rect","x":871,"y":1654,"width":1369,"height":875},"region_attributes":{"Descripteur":"cours.d'eau","Type":"objet"}},{"shape_attributes":{"name":"rect","x":618,"y":1477,"width":73,"height":73},"region_attributes":{"Descripteur":"croix","Type":"objet"}},{"shape_attributes":{"name":"rect","x":406,"y":323,"width":529,"height":536},"region_attributes":{"Descripteur":"nimbe","Type":"objet"}},{"shape_attributes":{"name":"rect","x":1534,"y":1702,"width":475,"height":231},"region_attributes":{"Descripteur":"poisson","Type":"objet"}},{"shape_attributes":{"name":"rect","x":1450,"y":1966,"width":852,"height":472},"region_attributes":{"Descripteur":"transparence","Type":"notion"}},{"shape_attributes":{"name":"rect","x":371,"y":1542,"width":253,"height":454},"region_attributes":{"Descripteur":"étoffe","Type":"notion"}}],"file_attributes":{"MandragoreId":"1029"}},"https://gallica.bnf.fr/iiif/ark:/12148/btv1b8419219x/f200/127,2582,2380,2038/full/0/native.jpg-1":{"filename":"https://gallica.bnf.fr/iiif/ark:/12148/btv1b8419219x/f200/127,2582,2380,2038/full/0/native.jpg","size":-1,"regions":[{"shape_attributes":{"name":"rect","x":15,"y":334,"width":719,"height":1450},"region_attributes":{"Descripteur":"arbre","Type":"objet"}},{"shape_attributes":{"name":"rect","x":866,"y":182,"width":520,"height":508},"region_attributes":{"Descripteur":"nimbe","Type":"objet"}},{"shape_attributes":{"name":"rect","x":786,"y":1346,"width":248,"height":365},"region_attributes":{"Descripteur":"étoffe","Type":"notion"}}],"file_attributes":{"MandragoreId":"1030"}},"https://gallica.bnf.fr/iiif/ark:/12148/btv1b8419219x/f204/146,2629,2285,1821/full/0/native.jpg-1":{"filename":"https://gallica.bnf.fr/iiif/ark:/12148/btv1b8419219x/f204/146,2629,2285,1821/full/0/native.jpg","size":-1,"regions":[{"shape_attributes":{"name":"rect","x":359,"y":140,"width":478,"height":305},"region_attributes":{"Descripteur":"couronne","Type":"objet"}},{"shape_attributes":{"name":"rect","x":957,"y":169,"width":241,"height":357},"region_attributes":{"Descripteur":"lampe","Type":"objet"}},{"shape_attributes":{"name":"rect","x":44,"y":151,"width":935,"height":1268},"region_attributes":{"Descripteur":"roi","Type":"objet"}},{"shape_attributes":{"name":"rect","x":1253,"y":188,"width":475,"height":259},"region_attributes":{"Descripteur":"turban","Type":"objet"}},{"shape_attributes":{"name":"rect","x":1976,"y":1244,"width":204,"height":372},"region_attributes":{"Descripteur":"vase","Type":"objet"}}],"file_attributes":{"MandragoreId":"1031"}},"https://gallica.bnf.fr/iiif/ark:/12148/btv1b8419219x/f208/113,2459,2434,2320/full/0/native.jpg-1":{"filename":"https://gallica.bnf.fr/iiif/ark:/12148/btv1b8419219x/f208/113,2459,2434,2320/full/0/native.jpg","size":-1,"regions":[{"shape_attributes":{"name":"rect","x":274,"y":114,"width":329,"height":234},"region_attributes":{"Descripteur":"casque","Type":"objet"}},{"shape_attributes":{"name":"rect","x":385,"y":519,"width":106,"height":988},"region_attributes":{"Descripteur":"épée","Type":"objet"}},{"shape_attributes":{"name":"rect","x":45,"y":1438,"width":614,"height":525},"region_attributes":{"Descripteur":"estrade","Type":"objet"}},{"shape_attributes":{"name":"rect","x":54,"y":81,"width":717,"height":1472},"region_attributes":{"Descripteur":"ascète","Type":"objet"}}],"file_attributes":{"MandragoreId":"1032"}},"https://gallica.bnf.fr/iiif/ark:/12148/btv1b8419219x/f218/120,2296,2385,2101/full/0/native.jpg-1":{"filename":"https://gallica.bnf.fr/iiif/ark:/12148/btv1b8419219x/f218/120,2296,2385,2101/full/0/native.jpg","size":-1,"regions":[{"shape_attributes":{"name":"rect","x":205,"y":349,"width":417,"height":263},"region_attributes":{"Descripteur":"couronne","Type":"objet"}},{"shape_attributes":{"name":"rect","x":101,"y":349,"width":857,"height":1199},"region_attributes":{"Descripteur":"roi","Type":"objet"}},{"shape_attributes":{"name":"rect","x":1781,"y":230,"width":389,"height":298},"region_attributes":{"Descripteur":"turban","Type":"objet"}},{"shape_attributes":{"name":"rect","x":28,"y":1530,"width":1033,"height":493},"region_attributes":{"Descripteur":"trône","Type":"objet"}}],"file_attributes":{"MandragoreId":"1033"}},"https://gallica.bnf.fr/iiif/ark:/12148/btv1b8419219x/f227/753,734,2467,1626/full/0/native.jpg-1":{"filename":"https://gallica.bnf.fr/iiif/ark:/12148/btv1b8419219x/f227/753,734,2467,1626/full/0/native.jpg","size":-1,"regions":[{"shape_attributes":{"name":"rect","x":842,"y":166,"width":456,"height":210},"region_attributes":{"Descripteur":"couronne","Type":"objet"}},{"shape_attributes":{"name":"rect","x":1437,"y":208,"width":177,"height":293},"region_attributes":{"Descripteur":"lampe","Type":"objet"}},{"shape_attributes":{"name":"rect","x":701,"y":162,"width":680,"height":1032},"region_attributes":{"Descripteur":"roi","Type":"personne"}},{"shape_attributes":{"name":"rect","x":701,"y":978,"width":776,"height":568},"region_attributes":{"Descripteur":"trône","Type":"objet"}},{"shape_attributes":{"name":"rect","x":308,"y":593,"width":254,"height":574},"region_attributes":{"Descripteur":"vase","Type":"objet"}},{"shape_attributes":{"name":"rect","x":2045,"y":1156,"width":389,"height":242},"region_attributes":{"Descripteur":"plateau","Type":"objet"}}],"file_attributes":{"MandragoreId":"1034"}},"https://gallica.bnf.fr/iiif/ark:/12148/btv1b8419219x/f262/101,2662,2383,1572/full/0/native.jpg-1":{"filename":"https://gallica.bnf.fr/iiif/ark:/12148/btv1b8419219x/f262/101,2662,2383,1572/full/0/native.jpg","size":-1,"regions":[{"shape_attributes":{"name":"rect","x":1297,"y":192,"width":390,"height":210},"region_attributes":{"Descripteur":"couronne","Type":"objet"}},{"shape_attributes":{"name":"rect","x":259,"y":309,"width":357,"height":323},"region_attributes":{"Descripteur":"turban","Type":"objet"}},{"shape_attributes":{"name":"rect","x":1953,"y":771,"width":236,"height":497},"region_attributes":{"Descripteur":"vase","Type":"objet"}},{"shape_attributes":{"name":"rect","x":929,"y":1092,"width":1014,"height":436},"region_attributes":{"Descripteur":"trône","Type":"objet"}}],"file_attributes":{"MandragoreId":"1035"}},"https://gallica.bnf.fr/iiif/ark:/12148/btv1b8419219x/f265/920,1402,2373,1571/full/0/native.jpg-1":{"filename":"https://gallica.bnf.fr/iiif/ark:/12148/btv1b8419219x/f265/920,1402,2373,1571/full/0/native.jpg","size":-1,"regions":[{"shape_attributes":{"name":"rect","x":116,"y":152,"width":660,"height":611},"region_attributes":{"Descripteur":"nimbe","Type":"objet"}},{"shape_attributes":{"name":"rect","x":832,"y":655,"width":1497,"height":830},"region_attributes":{"Descripteur":"prosternation","Type":"scène"}},{"shape_attributes":{"name":"rect","x":60,"y":184,"width":752,"height":1345},"region_attributes":{"Descripteur":"moine","Type":"objet"}},{"shape_attributes":{"name":"rect","x":11,"y":74,"width":1656,"height":1476},"region_attributes":{"Descripteur":"grotte","Type":"objet"}}],"file_attributes":{"MandragoreId":"1036"}},"https://gallica.bnf.fr/iiif/ark:/12148/btv1b8419219x/f276/181,2336,2407,2071/full/0/native.jpg-1":{"filename":"https://gallica.bnf.fr/iiif/ark:/12148/btv1b8419219x/f276/181,2336,2407,2071/full/0/native.jpg","size":-1,"regions":[{"shape_attributes":{"name":"rect","x":1884,"y":684,"width":169,"height":65},"region_attributes":{"Descripteur":"bijou","Type":"objet"}},{"shape_attributes":{"name":"rect","x":240,"y":1006,"width":352,"height":131},"region_attributes":{"Descripteur":"ceinture","Type":"objet"}},{"shape_attributes":{"name":"rect","x":1047,"y":345,"width":325,"height":183},"region_attributes":{"Descripteur":"coiffe","Type":"objet"}},{"shape_attributes":{"name":"rect","x":281,"y":372,"width":401,"height":183},"region_attributes":{"Descripteur":"couronne","Type":"objet"}},{"shape_attributes":{"name":"rect","x":73,"y":1347,"width":797,"height":639},"region_attributes":{"Descripteur":"trône","Type":"objet"}}],"file_attributes":{"MandragoreId":"1037"}},"https://gallica.bnf.fr/iiif/ark:/12148/btv1b8419219x/f309/795,644,2480,2070/full/0/native.jpg-1":{"filename":"https://gallica.bnf.fr/iiif/ark:/12148/btv1b8419219x/f309/795,644,2480,2070/full/0/native.jpg","size":-1,"regions":[{"shape_attributes":{"name":"rect","x":661,"y":421,"width":463,"height":191},"region_attributes":{"Descripteur":"couronne","Type":"objet"}},{"shape_attributes":{"name":"rect","x":1549,"y":1745,"width":862,"height":243},"region_attributes":{"Descripteur":"coussin","Type":"objet"}},{"shape_attributes":{"name":"rect","x":1173,"y":292,"width":247,"height":370},"region_attributes":{"Descripteur":"lampe","Type":"objet"}},{"shape_attributes":{"name":"rect","x":13,"y":65,"width":893,"height":1438},"region_attributes":{"Descripteur":"rideau","Type":"objet"}},{"shape_attributes":{"name":"rect","x":396,"y":414,"width":817,"height":1120},"region_attributes":{"Descripteur":"roi","Type":"objet"}},{"shape_attributes":{"name":"rect","x":107,"y":919,"width":1151,"height":1049},"region_attributes":{"Descripteur":"trône","Type":"objet"}},{"shape_attributes":{"name":"rect","x":1487,"y":563,"width":450,"height":272},"region_attributes":{"Descripteur":"turban","Type":"objet"}},{"shape_attributes":{"name":"rect","x":1164,"y":1601,"width":247,"height":363},"region_attributes":{"Descripteur":"vase","Type":"objet"}},{"shape_attributes":{"name":"rect","x":668,"y":893,"width":125,"height":151},"region_attributes":{"Descripteur":"fermail","Type":"objet"}}],"file_attributes":{"MandragoreId":"1038"}},"https://gallica.bnf.fr/iiif/ark:/12148/btv1b8419219x/f312/183,808,2360,2158/full/0/native.jpg-1":{"filename":"https://gallica.bnf.fr/iiif/ark:/12148/btv1b8419219x/f312/183,808,2360,2158/full/0/native.jpg","size":-1,"regions":[{"shape_attributes":{"name":"rect","x":1446,"y":1167,"width":309,"height":116},"region_attributes":{"Descripteur":"ceinture","Type":"objet"}},{"shape_attributes":{"name":"rect","x":149,"y":453,"width":418,"height":211},"region_attributes":{"Descripteur":"couronne","Type":"objet"}},{"shape_attributes":{"name":"rect","x":86,"y":835,"width":413,"height":216},"region_attributes":{"Descripteur":"fourrure","Type":"objet"}},{"shape_attributes":{"name":"rect","x":731,"y":464,"width":385,"height":258},"region_attributes":{"Descripteur":"turban","Type":"objet"}},{"shape_attributes":{"name":"rect","x":18,"y":885,"width":846,"height":1222},"region_attributes":{"Descripteur":"trône","Type":"objet"}}],"file_attributes":{"MandragoreId":"1039"}},"https://gallica.bnf.fr/iiif/ark:/12148/btv1b8419219x/f324/177,2277,2391,1771/full/0/native.jpg-1":{"filename":"https://gallica.bnf.fr/iiif/ark:/12148/btv1b8419219x/f324/177,2277,2391,1771/full/0/native.jpg","size":-1,"regions":[{"shape_attributes":{"name":"rect","x":1354,"y":183,"width":207,"height":362},"region_attributes":{"Descripteur":"lampe","Type":"objet"}},{"shape_attributes":{"name":"rect","x":1814,"y":8,"width":575,"height":1005},"region_attributes":{"Descripteur":"rideau","Type":"objet"}},{"shape_attributes":{"name":"rect","x":489,"y":335,"width":868,"height":1100},"region_attributes":{"Descripteur":"roi","Type":"personne"}},{"shape_attributes":{"name":"rect","x":1599,"y":383,"width":366,"height":230},"region_attributes":{"Descripteur":"turban","Type":"objet"}},{"shape_attributes":{"name":"rect","x":86,"y":925,"width":333,"height":543},"region_attributes":{"Descripteur":"vase","Type":"objet"}},{"shape_attributes":{"name":"rect","x":1468,"y":746,"width":748,"height":782},"region_attributes":{"Descripteur":"vêtement","Type":"objet"}},{"shape_attributes":{"name":"rect","x":427,"y":1384,"width":897,"height":327},"region_attributes":{"Descripteur":"trône","Type":"objet"}}],"file_attributes":{"MandragoreId":"1040"}},"https://gallica.bnf.fr/iiif/ark:/12148/btv1b8419219x/f330/101,1430,2461,1974/full/0/native.jpg-1":{"filename":"https://gallica.bnf.fr/iiif/ark:/12148/btv1b8419219x/f330/101,1430,2461,1974/full/0/native.jpg","size":-1,"regions":[{"shape_attributes":{"name":"rect","x":1104,"y":127,"width":1242,"height":1161},"region_attributes":{"Descripteur":"baptême","Type":"scène"}},{"shape_attributes":{"name":"rect","x":1682,"y":635,"width":170,"height":966},"region_attributes":{"Descripteur":"canne","Type":"objet"}},{"shape_attributes":{"name":"rect","x":960,"y":403,"width":873,"height":1157},"region_attributes":{"Descripteur":"chasuble","Type":"objet"}},{"shape_attributes":{"name":"rect","x":522,"y":386,"width":355,"height":170},"region_attributes":{"Descripteur":"coiffe","Type":"objet"}},{"shape_attributes":{"name":"rect","x":134,"y":448,"width":386,"height":272},"region_attributes":{"Descripteur":"couronne","Type":"objet"}},{"shape_attributes":{"name":"rect","x":1185,"y":1423,"width":59,"height":68},"region_attributes":{"Descripteur":"croix","Type":"objet"}},{"shape_attributes":{"name":"rect","x":1006,"y":1561,"width":760,"height":321},"region_attributes":{"Descripteur":"estrade","Type":"objet"}},{"shape_attributes":{"name":"rect","x":1799,"y":752,"width":582,"height":1138},"region_attributes":{"Descripteur":"fonts","Type":"objet"}},{"shape_attributes":{"name":"rect","x":1852,"y":427,"width":480,"height":408},"region_attributes":{"Descripteur":"nimbe","Type":"objet"}},{"shape_attributes":{"name":"rect","x":13,"y":868,"width":718,"height":1023},"region_attributes":{"Descripteur":"vêtement","Type":"objet"}}],"file_attributes":{"MandragoreId":"1041"}},"https://gallica.bnf.fr/iiif/ark:/12148/btv1b8419219x/f338/158,816,2411,1797/full/0/native.jpg-1":{"filename":"https://gallica.bnf.fr/iiif/ark:/12148/btv1b8419219x/f338/158,816,2411,1797/full/0/native.jpg","size":-1,"regions":[{"shape_attributes":{"name":"rect","x":504,"y":226,"width":413,"height":238},"region_attributes":{"Descripteur":"couronne","Type":"objet"}},{"shape_attributes":{"name":"rect","x":118,"y":222,"width":929,"height":1103},"region_attributes":{"Descripteur":"roi","Type":"objet"}},{"shape_attributes":{"name":"rect","x":77,"y":952,"width":1047,"height":759},"region_attributes":{"Descripteur":"trône","Type":"objet"}},{"shape_attributes":{"name":"rect","x":1509,"y":238,"width":417,"height":236},"region_attributes":{"Descripteur":"coiffe","Type":"objet"}},{"shape_attributes":{"name":"rect","x":294,"y":1112,"width":653,"height":183},"region_attributes":{"Descripteur":"étoffe","Type":"notion"}}],"file_attributes":{"MandragoreId":"1042"}},"https://gallica.bnf.fr/iiif/ark:/12148/btv1b8419219x/f341/702,1309,2599,2333/full/0/native.jpg-1":{"filename":"https://gallica.bnf.fr/iiif/ark:/12148/btv1b8419219x/f341/702,1309,2599,2333/full/0/native.jpg","size":-1,"regions":[{"shape_attributes":{"name":"rect","x":582,"y":416,"width":507,"height":346},"region_attributes":{"Descripteur":"couronne","Type":"objet"}},{"shape_attributes":{"name":"rect","x":1520,"y":10,"width":216,"height":246},"region_attributes":{"Descripteur":"croix","Type":"objet"}},{"shape_attributes":{"name":"rect","x":304,"y":424,"width":883,"height":1259},"region_attributes":{"Descripteur":"roi","Type":"objet"}},{"shape_attributes":{"name":"rect","x":283,"y":1698,"width":906,"height":539},"region_attributes":{"Descripteur":"trône","Type":"objet"}},{"shape_attributes":{"name":"rect","x":1370,"y":655,"width":344,"height":329},"region_attributes":{"Descripteur":"turban","Type":"objet"}}],"file_attributes":{"MandragoreId":"1043"}},"https://gallica.bnf.fr/iiif/ark:/12148/btv1b8419219x/f347/896,696,2398,2043/full/0/native.jpg-1":{"filename":"https://gallica.bnf.fr/iiif/ark:/12148/btv1b8419219x/f347/896,696,2398,2043/full/0/native.jpg","size":-1,"regions":[{"shape_attributes":{"name":"rect","x":1397,"y":1179,"width":66,"height":94},"region_attributes":{"Descripteur":"croix","Type":"objet"}},{"shape_attributes":{"name":"rect","x":1919,"y":424,"width":259,"height":371},"region_attributes":{"Descripteur":"lampe","Type":"objet"}},{"shape_attributes":{"name":"rect","x":1267,"y":382,"width":373,"height":393},"region_attributes":{"Descripteur":"nimbe","Type":"objet"}},{"shape_attributes":{"name":"rect","x":733,"y":354,"width":549,"height":1594},"region_attributes":{"Descripteur":"roi","Type":"objet"}},{"shape_attributes":{"name":"rect","x":1834,"y":1526,"width":498,"height":321},"region_attributes":{"Descripteur":"vase","Type":"objet"}},{"shape_attributes":{"name":"rect","x":1278,"y":729,"width":437,"height":1131},"region_attributes":{"Descripteur":"vêtement","Type":"objet"}},{"shape_attributes":{"name":"rect","x":1278,"y":378,"width":496,"height":1595},"region_attributes":{"Descripteur":"ascète","Type":"objet"}}],"file_attributes":{"MandragoreId":"1044"}},"https://gallica.bnf.fr/iiif/ark:/12148/btv1b8419219x/f358/196,786,2445,1996/full/0/native.jpg-1":{"filename":"https://gallica.bnf.fr/iiif/ark:/12148/btv1b8419219x/f358/196,786,2445,1996/full/0/native.jpg","size":-1,"regions":[{"shape_attributes":{"name":"rect","x":1541,"y":116,"width":756,"height":1734},"region_attributes":{"Descripteur":"arbre","Type":"objet"}},{"shape_attributes":{"name":"rect","x":1226,"y":1185,"width":86,"height":97},"region_attributes":{"Descripteur":"croix","Type":"objet"}},{"shape_attributes":{"name":"rect","x":700,"y":172,"width":462,"height":466},"region_attributes":{"Descripteur":"nimbe","Type":"objet"}},{"shape_attributes":{"name":"rect","x":1002,"y":535,"width":696,"height":1249},"region_attributes":{"Descripteur":"vêtement","Type":"objet"}}],"file_attributes":{"MandragoreId":"1045"}},"https://gallica.bnf.fr/iiif/ark:/12148/btv1b8419219x/f1/18,37,3474,5050/full/0/native.jpg-1":{"filename":"https://gallica.bnf.fr/iiif/ark:/12148/btv1b8419219x/f1/18,37,3474,5050/full/0/native.jpg","size":-1,"regions":[],"file_attributes":{"MandragoreId":"190989"}},"https://gallica.bnf.fr/iiif/ark:/12148/btv1b8419219x/f388/89,38,3466,5126/full/0/native.jpg-1":{"filename":"https://gallica.bnf.fr/iiif/ark:/12148/btv1b8419219x/f388/89,38,3466,5126/full/0/native.jpg","size":-1,"regions":[],"file_attributes":{"MandragoreId":"190990"}}}